pgqb/__init__.py
pgqb/_snake.py
pgqb/builder.py
pgqb/py.typed
pgqb/types.py
pgqb-0.1.0.dist-info/METADATA
pgqb-0.1.0.dist-info/WHEEL
pgqb-0.1.0.dist-info/licenses/LICENSE
pgqb-0.1.0.dist-info/RECORD
